pg_scheduler/__init__.py
pg_scheduler/examples.py
pg_scheduler/scheduler.py
pg_scheduler-0.1.0.dist-info/LICENSE
pg_scheduler-0.1.0.dist-info/METADATA
pg_scheduler-0.1.0.dist-info/WHEEL
pg_scheduler-0.1.0.dist-info/top_level.txt
pg_scheduler-0.1.0.dist-info/RECORD
