Metadata-Version: 2.1
Name: pg-scheduler
Version: 0.1.0
Summary: A PostgreSQL-based async job scheduler with deduplication, periodic jobs, and reliability features
Author-email: Miguel Rebelo <miguel.python.dev@gmail.com>
Maintainer-email: Miguel Rebelo <miguel.python.dev@gmail.com>
Project-URL: Homepage, https://github.com/m1guelvrrl0/pg-scheduler
Project-URL: Documentation, https://github.com/m1guelvrrl0/pg-scheduler#readme
Project-URL: Repository, https://github.com/m1guelvrrl0/pg-scheduler.git
Project-URL: Bug Tracker, https://github.com/m1guelvrrl0/pg-scheduler/issues
Project-URL: Changelog, https://github.com/m1guelvrrl0/pg-scheduler/blob/main/CHANGELOG.md
Keywords: postgresql,job-scheduler,async,periodic-jobs,task-queue,deduplication,reliability,distributed
Classifier: Development Status :: 4 - Beta
Classifier: Intended Audience :: Developers
Classifier: License :: OSI Approved :: MIT License
Classifier: Programming Language :: Python :: 3
Classifier: Programming Language :: Python :: 3.9
Classifier: Programming Language :: Python :: 3.10
Classifier: Programming Language :: Python :: 3.11
Classifier: Programming Language :: Python :: 3.12
Classifier: Programming Language :: Python :: 3.13
Classifier: Topic :: Software Development :: Libraries :: Python Modules
Classifier: Topic :: Database
Classifier: Topic :: System :: Distributed Computing
Classifier: Framework :: AsyncIO
Classifier: Operating System :: OS Independent
Requires-Python: >=3.9
License-File: LICENSE
Requires-Dist: asyncpg>=0.25.0
Provides-Extra: dev
Requires-Dist: pytest>=7.0; extra == "dev"
Requires-Dist: pytest-asyncio>=0.21.0; extra == "dev"
Requires-Dist: black>=22.0; extra == "dev"
Requires-Dist: isort>=5.0; extra == "dev"
Requires-Dist: mypy>=1.0; extra == "dev"
Requires-Dist: flake8>=5.0; extra == "dev"
Provides-Extra: examples
Requires-Dist: fastapi>=0.68.0; extra == "examples"
Requires-Dist: uvicorn>=0.15.0; extra == "examples"
